{"services": [{"name": "Joomla", "description": "Joomla is a free and open-source content management system for publishing web content on websites.", "tags": ["CMS"], "source": "https://github.com/joomla/joomla-cms", "website": "https://joomla.org", "icon": "https://docs.joomla.org/images/0/02/Joomla-flat-logo-en.png", "screenshots": ["https://upload.wikimedia.org/wikipedia/commons/9/96/Backend_Joomla_4_en.png"], "stars": 4460, "forks": 3593, "watchers": 4460, "issues": 1003, "last_updated": "2023-05-30T07:17:20Z", "last_pushed": "2023-05-30T20:11:57Z", "created_at": "2011-09-27T02:07:38Z", "size": 322543, "language": "PHP", "gitops": false, "status": "active", "license": "GNU General Public License v2.0", "spdx_id": "GPL-2.0", "dirname": "joomla"}, {"name": "NocoDB", "description": "The Open Source Airtable Alternative. Turns any MySQL, PostgreSQL, SQL Server, SQLite & MariaDB into a smart-spreadsheet.", "tags": ["low-code", "admin-dashboard", "no-code", "admin-ui"], "source": "https://github.com/nocodb/nocodb", "website": "https://www.nocodb.com", "icon": "https://raw.githubusercontent.com/nocodb/nocodb/develop/packages/nc-gui/assets/img/icons/512x512.png", "screenshots": ["https://user-images.githubusercontent.com/35857179/194844858-d353bd15-1edf-406c-889b-ba60f76831f4.png", "https://user-images.githubusercontent.com/35857179/194844872-1a1094b9-761b-4ab6-a0ab-8e11dcae6571.png", "https://user-images.githubusercontent.com/35857179/194844881-23f12c4c-7a5f-403e-928c-ef4c53b2665d.png", "https://user-images.githubusercontent.com/35857179/194844885-faaf042f-bad2-4924-84f0-2c08813271d8.png", "https://user-images.githubusercontent.com/35857179/194844886-a17006e0-979d-493f-83c4-0e72f5a9b716.png", "https://user-images.githubusercontent.com/35857179/194844890-b9f265ae-6e40-4fa5-9267-d1367c27c8e6.png", "https://user-images.githubusercontent.com/35857179/194844903-c1e47f40-e782-4f5d-8dce-6449cc70b181.png"], "stars": 36240, "forks": 2309, "watchers": 36240, "issues": 459, "last_updated": "2023-05-30T18:22:48Z", "last_pushed": "2023-05-30T20:11:21Z", "created_at": "2017-10-29T18:51:48Z", "size": 927590, "language": "TypeScript", "gitops": false, "status": "active", "license": "GNU Affero General Public License v3.0", "spdx_id": "AGPL-3.0", "dirname": "nocodb"}, {"name": "Nats", "description": "Connective Technology for Adaptive Edge & Distributed Systems", "tags": ["network", "pubsub", "microservices"], "source": "https://github.com/nats-io/nats-server", "website": "https://nats.io", "icon": "https://avatars.githubusercontent.com/u/10203055?s=200&v=4", "screenshots": [], "stars": 12842, "forks": 1240, "watchers": 12842, "issues": 279, "last_updated": "2023-05-30T18:26:58Z", "last_pushed": "2023-05-30T20:09:52Z", "created_at": "2012-10-29T16:12:24Z", "size": 33207, "language": "Go", "gitops": false, "status": "active", "license": "Apache License 2.0", "spdx_id": "Apache-2.0", "dirname": "nats"}, {"name": "Grafana", "description": "Gatus is a service that allows you to monitor the availability and latency of your services and expose this information a beautiful dashboard.", "tags": ["monitoring", "metrics", "dashboard"], "source": "https://github.com/grafana/grafana", "website": "https://grafana.com/", "icon": "https://raw.githubusercontent.com/devicons/devicon/1119b9f84c0290e0f0b38982099a2bd027a48bf1/icons/grafana/grafana-original.svg", "screenshots": ["https://upload.wikimedia.org/wikipedia/commons/thumb/b/b3/Grafana_screenshot.png/800px-Grafana_screenshot.png", "https://upload.wikimedia.org/wikipedia/commons/thumb/8/89/Grafana_dashboard.png/800px-Grafana_dashboard.png"], "stars": 55552, "forks": 10875, "watchers": 55552, "issues": 3583, "last_updated": "2023-05-30T19:52:36Z", "last_pushed": "2023-05-30T20:03:53Z", "created_at": "2013-12-11T15:59:56Z", "size": 785448, "language": "TypeScript", "gitops": false, "status": "active", "license": "GNU Affero General Public License v3.0", "spdx_id": "AGPL-3.0", "dirname": "grafana"}, {"name": "gitea", "description": "Painless self-hosted all-in-one software development service, includes Git hosting, code review, team collaboration, package registry and CI/CD", "tags": ["git repository", "git"], "source": "https://github.com/go-gitea/gitea", "website": "https://gitea.io/", "icon": "https://gitea.io/images/gitea.png", "screenshots": ["https://gitea.io/images/screenshot.png", "https://camo.githubusercontent.com/134f49a62801ab393c211125515d108439c67b59befb2ec3e42e7235af4f5d6c/68747470733a2f2f646c2e67697465612e696f2f73637265656e73686f74732f686f6d655f74696d656c696e652e706e67", "https://camo.githubusercontent.com/186c2a4c286dcb5e6c419ae11c062721ba73eafcc40e518f237adcc9985385db/68747470733a2f2f646c2e67697465612e696f2f73637265656e73686f74732f757365725f70726f66696c652e706e67"], "stars": 36830, "forks": 4655, "watchers": 36830, "issues": 2124, "last_updated": "2023-05-30T20:07:52Z", "last_pushed": "2023-05-30T20:02:08Z", "created_at": "2016-11-01T02:13:26Z", "size": 281680, "language": "Go", "gitops": false, "status": "active", "license": "MIT License", "spdx_id": "MIT", "dirname": "gitea"}, {"name": "Appsmith", "description": "Low code project to build admin panels, internal tools, and dashboards. Integrates with 15+ databases and any API.", "tags": ["admin-dashboard", "workflows", "app-builder"], "source": "https://github.com/appsmithorg/appsmith", "website": "https://www.appsmith.com", "icon": "https://avatars.githubusercontent.com/u/67620218?s=200&v=4", "screenshots": ["https://images.ctfassets.net/lpvian6u6i39/57xRxbPxLB5Rx6YYCQstyW/d605683e09640cabbb15e9a9d65dc03d/img-cta.png"], "stars": 27434, "forks": 2717, "watchers": 27434, "issues": 3171, "last_updated": "2023-05-30T19:14:24Z", "last_pushed": "2023-05-30T20:01:17Z", "created_at": "2020-06-30T04:07:36Z", "size": 355090, "language": "TypeScript", "gitops": false, "status": "active", "license": "Apache License 2.0", "spdx_id": "Apache-2.0", "dirname": "appsmith"}, {"name": "Stirling PDF", "description": "Stirling PDF is a hosted web application that allows you to perform various operations on PDF files, such as splitting and adding images.", "tags": ["PDF"], "source": "https://github.com/Frooodle/Stirling-PDF", "website": "https://github.com/Frooodle/Stirling-PDF", "icon": "https://raw.githubusercontent.com/Frooodle/Stirling-PDF/main/docs/stirling.png", "screenshots": ["https://raw.githubusercontent.com/Frooodle/Stirling-PDF/main/images/stirling-home.png"], "stars": 938, "forks": 54, "watchers": 938, "issues": 35, "last_updated": "2023-05-30T17:36:06Z", "last_pushed": "2023-05-30T19:55:09Z", "created_at": "2023-01-27T18:22:42Z", "size": 6098, "language": "HTML", "gitops": false, "status": "active", "license": "GNU General Public License v3.0", "spdx_id": "GPL-3.0", "dirname": "sterlingpdf"}, {"name": "WordPress", "description": "WordPress is a free and open-source content management system written in hypertext preprocessor language.", "tags": ["Search"], "source": "https://github.com/WordPress/WordPress", "website": "https://github.com/benbusby/whoogle-search", "icon": "https://avatars.githubusercontent.com/u/276006?s=280", "screenshots": ["https://wordpress.org/documentation/files/2021/07/test-widgets_v2-1-1024x643.jpeg", "https://user-images.githubusercontent.com/12400734/168248949-f19a1a73-2c02-4eab-84d1-faaff57dbd07.png", "https://wordpress.org/documentation/files/2021/06/menu-add-items-1024x557.png"], "stars": 17535, "forks": 12284, "watchers": 17535, "issues": 2, "last_updated": "2023-05-30T15:54:10Z", "last_pushed": "2023-05-30T19:54:05Z", "created_at": "2011-12-01T07:05:17Z", "size": 400431, "language": "PHP", "gitops": false, "status": "active", "license": "Other", "spdx_id": "NOASSERTION", "dirname": "wordpress"}, {"name": "Symfony", "description": "Symfony is a PHP framework for web and console applications and a set of reusable PHP components.", "tags": ["framework", "php"], "source": "https://github.com/symfony/symfony", "website": "https://symfony.com", "icon": "https://avatars.githubusercontent.com/u/143937?s=200&v=4", "screenshots": null, "stars": 28382, "forks": 9099, "watchers": 28382, "issues": 792, "last_updated": "2023-05-30T20:07:30Z", "last_pushed": "2023-05-30T19:48:30Z", "created_at": "2010-01-04T14:21:21Z", "size": 254138, "language": "PHP", "gitops": true, "status": "active", "license": "MIT License", "spdx_id": "MIT", "dirname": "symfony"}, {"name": "Coral", "description": "A better onlne commenting experience from Vox Media", "tags": ["commments", "community"], "source": "https://github.com/coralproject/talk", "website": "https://coralproject.net", "documentation": ["https://docs.coralproject.net/", "https://github.com/coralproject/talk/blob/main/docs/docs/environment-variables.md"], "icon": "https://avatars.githubusercontent.com/u/9255912?s=200&v=4", "screenshots": null, "stars": 1835, "forks": 359, "watchers": 1835, "issues": 33, "last_updated": "2023-05-27T21:13:20Z", "last_pushed": "2023-05-30T19:31:53Z", "created_at": "2016-10-31T16:14:05Z", "size": 66317, "language": "TypeScript", "gitops": false, "status": "active", "license": "Other", "spdx_id": "NOASSERTION", "dirname": "coral"}, {"name": "Ghost", "description": "Ghost is a powerful app for new-media creators to publish, share, and grow a business around their content.", "tags": ["CMS", "Blogging", "Publishing"], "source": "https://github.com/TryGhost/Ghost", "website": "https://ghost.org/", "icon": "https://ghost.org/images/logos/ghost-logo-orb.png", "screenshots": ["https://user-images.githubusercontent.com/353959/169805900-66be5b89-0859-4816-8da9-528ed7534704.png"], "stars": 43308, "forks": 9421, "watchers": 43308, "issues": 128, "last_updated": "2023-05-30T19:57:58Z", "last_pushed": "2023-05-30T19:12:25Z", "created_at": "2013-05-04T11:09:13Z", "size": 237148, "language": "JavaScript", "gitops": false, "status": "active", "license": "MIT License", "spdx_id": "MIT", "dirname": "ghost"}, {"name": "Meilisearch", "description": "A lightning-fast search engine that fits effortlessly into your apps, websites, and workflow ", "tags": ["search"], "source": "https://github.com/meilisearch/meilisearch", "website": "https://www.meilisearch.com/", "icon": "https://www.meilisearch.com/apple-touch-icon.png", "screenshots": ["https://github.com/meilisearch/meilisearch/raw/main/assets/demo-light.gif"], "stars": 36737, "forks": 1333, "watchers": 36737, "issues": 136, "last_updated": "2023-05-30T20:05:51Z", "last_pushed": "2023-05-30T18:57:53Z", "created_at": "2018-04-23T11:45:28Z", "size": 54371, "language": "Rust", "gitops": false, "status": "active", "license": "MIT License", "spdx_id": "MIT", "dirname": "meilisearch"}, {"name": "NTFY", "description": "ntfy (pronounced \"notify\") is a simple HTTP-based pub-sub notification service. With ntfy, you can send notifications to your phone or desktop via scripts from any computer, without having to sign up or pay any fees", "tags": ["notifications", "push", "pubsub"], "source": "https://github.com/binwiederhier/ntfy", "website": "https://ntfy.sh/", "icon": "https://ntfy.sh/_next/static/media/logo.077f6a13.svg", "screenshots": ["https://ntfy.sh/static/img/screenshot-web-detail.png", "https://ntfy.sh/static/img/screenshot-curl.png", "https://ntfy.sh/static/img/screenshot-phone-notification.jpg", "https://ntfy.sh/static/img/screenshot-phone-detail.jpg"], "stars": 10684, "forks": 358, "watchers": 10684, "issues": 105, "last_updated": "2023-05-30T15:29:59Z", "last_pushed": "2023-05-30T18:53:33Z", "created_at": "2021-10-23T19:25:32Z", "size": 30199, "language": "Go", "gitops": false, "status": "active", "license": "Apache License 2.0", "spdx_id": "Apache-2.0", "dirname": "ntfy"}, {"name": "LanguageTool", "description": "LanguageTool is an Open Source proofreading software for English, Spanish, French, German, Portuguese, Polish, Dutch, and more than 20 other languages.", "tags": ["spellcheck", "grammar"], "source": "https://github.com/languagetool-org/languagetool", "website": "https://languagetool.org/", "icon": "https://avatars.githubusercontent.com/u/5187764?s=200&v=4", "documentation": ["https://github.com/Erikvl87/docker-languagetool/blob/master/docker-compose.yml"], "screenshots": ["https://languagetool.org/videos/gmail_de_en.mp4"], "stars": 8655, "forks": 1058, "watchers": 8655, "issues": 1842, "last_updated": "2023-05-30T14:49:51Z", "last_pushed": "2023-05-30T18:39:52Z", "created_at": "2013-08-08T16:37:22Z", "size": 4470553, "language": "Java", "gitops": false, "status": "active", "license": "GNU Lesser General Public License v2.1", "spdx_id": "LGPL-2.1", "dirname": "languagetool"}, {"name": "Excalidraw", "description": "An open source virtual hand-drawn style whiteboard. Collaborative and end-to-end encrypted.", "tags": ["drawing", "collaboration", "whiteboard"], "source": "https://github.com/excalidraw/excalidraw", "website": "https://excalidraw.com/", "icon": "https://avatars.githubusercontent.com/u/59452120?s=200&v=4", "screenshots": ["https://excalidraw.nyc3.cdn.digitaloceanspaces.com/github%2Fproduct_showcase.png"], "stars": 48962, "forks": 4180, "watchers": 48962, "issues": 1056, "last_updated": "2023-05-30T19:19:40Z", "last_pushed": "2023-05-30T18:29:22Z", "created_at": "2020-01-02T01:04:43Z", "size": 42954, "language": "TypeScript", "gitops": false, "status": "active", "license": "MIT License", "spdx_id": "MIT", "dirname": "excalidraw"}, {"name": "phpMyAdmin", "description": "phpMyAdmin is a free software tool written in PHP, intended to handle the administration of MySQL and MariaDB over the Web.", "tags": ["database", "administration"], "source": "https://github.com/phpmyadmin/phpmyadmin", "website": "https://www.phpmyadmin.net/", "icon": "https://avatars.githubusercontent.com/u/1351977?s=200&v=4", "screenshots": ["https://upload.wikimedia.org/wikipedia/commons/1/13/PhpMyAdmin-main-en.png"], "stars": 6587, "forks": 3334, "watchers": 6587, "issues": 695, "last_updated": "2023-05-30T18:14:07Z", "last_pushed": "2023-05-30T18:04:04Z", "created_at": "2012-01-19T13:21:52Z", "size": 1615394, "language": "PHP", "gitops": false, "status": "active", "license": "GNU General Public License v2.0", "spdx_id": "GPL-2.0", "dirname": "phpmyadmin"}, {"name": "Trilium Notes", "description": "Trilium Notes is a hierarchical note taking application with focus on building large personal knowledge bases. ", "tags": ["note taking", "knowledge base"], "source": "https://github.com/zadam/trilium", "website": "https://github.com/zadam/trilium", "icon": "https://raw.githubusercontent.com/zadam/trilium/master/images/app-icons/png/256x256.png", "screenshots": ["https://raw.githubusercontent.com/wiki/zadam/trilium/images/screenshot.png"], "stars": 21427, "forks": 1430, "watchers": 21427, "issues": 841, "last_updated": "2023-05-30T18:54:07Z", "last_pushed": "2023-05-30T17:57:07Z", "created_at": "2017-05-23T00:30:20Z", "size": 110749, "language": "JavaScript", "gitops": false, "status": "active", "license": "GNU Affero General Public License v3.0", "spdx_id": "AGPL-3.0", "dirname": "trilium"}, {"name": "Hoppscotch", "description": "Open source API development ecosystem", "tags": ["development"], "source": "https://github.com/hoppscotch/hoppscotch", "website": "https://hoppscotch.io", "icon": "https://avatars.githubusercontent.com/u/56705483?s=200&v=4", "screenshots": ["https://raw.githubusercontent.com/hoppscotch/hoppscotch/main/packages/hoppscotch-common/public/images/banner-light.png"], "stars": 51666, "forks": 3549, "watchers": 51666, "issues": 144, "last_updated": "2023-05-30T20:12:26Z", "last_pushed": "2023-05-30T17:36:25Z", "created_at": "2019-08-21T13:15:24Z", "size": 67766, "language": "TypeScript", "gitops": false, "status": "active", "license": "MIT License", "spdx_id": "MIT", "dirname": "hopscotch"}, {"name": "Photoview", "description": "Photoview is a simple and user-friendly photo gallery that is made for photographers and aims to provide an easy and fast way to navigate directories.", "tags": ["imaga database"], "source": "https://github.com/photoview/photoview", "website": "https://photoview.github.io/", "icon": "https://avatars.githubusercontent.com/u/75802894?s=200&v=4", "screenshots": ["https://raw.githubusercontent.com/photoview/photoview/master/screenshots/timeline.png"], "stars": 3850, "forks": 304, "watchers": 3850, "issues": 204, "last_updated": "2023-05-30T17:50:27Z", "last_pushed": "2023-05-30T17:04:25Z", "created_at": "2019-07-07T13:55:00Z", "size": 50334, "language": "TypeScript", "gitops": false, "status": "active", "license": "GNU Affero General Public License v3.0", "spdx_id": "AGPL-3.0", "dirname": "photoview"}, {"name": "Homarr", "description": "Homarr is a simple and lightweight homepage for your server, that helps you easily access all of your services in one place.", "tags": ["homepage"], "source": "https://github.com/ajnart/homarr", "website": "https://homarr.dev", "icon": "https://github.com/ajnart/homarr/raw/dev/public/imgs/logo/logo-color.svg", "screenshots": ["https://user-images.githubusercontent.com/71191962/169860380-856634fb-4f41-47cb-ba54-6a9e7b3b9c81.gif"], "stars": 2260, "forks": 112, "watchers": 2260, "issues": 100, "last_updated": "2023-05-30T18:57:10Z", "last_pushed": "2023-05-30T16:22:05Z", "created_at": "2022-04-24T20:36:46Z", "size": 9987, "language": "TypeScript", "gitops": false, "status": "active", "license": "MIT License", "spdx_id": "MIT", "dirname": "homarr"}, {"name": "MongoDB Express", "description": "Web-based MongoDB admin interface written with Node.js, Express and Bootstrap3", "tags": ["database administration"], "source": "https://github.com/mongo-express/mongo-express", "website": "https://github.com/mongo-express/mongo-express", "icon": "https://avatars.githubusercontent.com/u/17328297?s=200&v=4", "screenshots": ["http://i.imgur.com/XiYhblA.png", "http://i.imgur.com/XWcIgY1.png", "https://imgur.com/UmGSr3x.png", "https://imgur.com/lL38abn.png"], "stars": 5008, "forks": 905, "watchers": 5008, "issues": 160, "last_updated": "2023-05-30T19:07:57Z", "last_pushed": "2023-05-30T15:58:08Z", "created_at": "2012-04-23T20:11:25Z", "size": 8651, "language": "JavaScript", "gitops": false, "status": "active", "license": "MIT License", "spdx_id": "MIT", "dirname": "mongodb-express"}, {"name": "Docker Registry", "description": "The Registry is a stateless, highly scalable server side application that stores and lets you distribute Docker images.", "tags": ["docker"], "source": "https://github.com/distribution/distribution", "website": "https://docs.docker.com/registry/", "icon": "https://avatars.githubusercontent.com/u/5429470?s=200&v=4", "screenshots": null, "stars": 7565, "forks": 2278, "watchers": 7565, "issues": 761, "last_updated": "2023-05-30T13:17:01Z", "last_pushed": "2023-05-30T13:12:49Z", "created_at": "2014-12-22T23:49:26Z", "size": 25137, "language": "Go", "gitops": false, "status": "active", "license": "Apache License 2.0", "spdx_id": "Apache-2.0", "dirname": "dockerregistry"}, {"name": "Kuma", "description": "Kuma is a self-hosted monitoring tool like \"Uptime Robot\". ", "tags": ["monitoring"], "source": "https://github.com/louislam/uptime-kuma", "website": "https://uptime.kuma.pet", "icon": "https://github.com/louislam/uptime-kuma/raw/master/public/icon.svg", "screenshots": ["https://camo.githubusercontent.com/9674a2b1b7d094b060fd79e6df7dca10b86a484ce6015b2668cff768dfc786ee/68747470733a2f2f757074696d652e6b756d612e7065742f696d672f6461726b2e6a7067"], "stars": 33856, "forks": 2919, "watchers": 33856, "issues": 926, "last_updated": "2023-05-30T20:08:54Z", "last_pushed": "2023-05-30T13:06:59Z", "created_at": "2021-07-03T01:02:42Z", "size": 17557, "language": "JavaScript", "gitops": false, "status": "active", "license": "MIT License", "spdx_id": "MIT", "dirname": "kuma"}, {"name": "Memos", "description": "Memos is a simple note taking app. ", "tags": ["note taking"], "source": "https://github.com/usememos/memos", "website": "https://usememos.com/", "icon": "https://avatars.githubusercontent.com/u/95764151?s=200&v=4", "screenshots": ["https://usememos.com/demo.webp"], "stars": 14256, "forks": 953, "watchers": 14256, "issues": 148, "last_updated": "2023-05-30T19:13:56Z", "last_pushed": "2023-05-30T12:45:45Z", "created_at": "2021-12-08T15:30:18Z", "size": 9849, "language": "TypeScript", "gitops": false, "status": "active", "license": "MIT License", "spdx_id": "MIT", "dirname": "memos"}, {"name": "Homebox", "description": "Homebox is the inventory and organization system built for the Home User", "tags": ["Search"], "source": "https://github.com/hay-kot/homebox", "website": "hay-kot.github.io/homebox/", "icon": "https://raw.githubusercontent.com/hay-kot/homebox/main/docs/docs/assets/img/lilbox.svg", "screenshots": null, "stars": 1002, "forks": 46, "watchers": 1002, "issues": 76, "last_updated": "2023-05-30T18:55:57Z", "last_pushed": "2023-05-30T10:08:11Z", "created_at": "2022-08-30T02:30:35Z", "size": 3746, "language": "Go", "gitops": false, "status": "active", "license": "GNU Affero General Public License v3.0", "spdx_id": "AGPL-3.0", "dirname": "homebox"}, {"name": "Illa", "description": "ILLA is a robust open source low-code platform for developers to build internal tools.", "tags": ["low-code"], "source": "https://github.com/illacloud/illa-builder", "website": "https://illacloud.com", "icon": "https://www.illacloud.com/favicons/apple-touch-icon.png?v=3", "screenshots": ["https://www.illacloud.com/_next/image?url=https%3A%2F%2Fcdn.illacloud.com%2Fofficial-website%2Fimg%2Fhome%2FplayVideoCover.png&w=3840&q=75"], "stars": 6620, "forks": 408, "watchers": 6620, "issues": 33, "last_updated": "2023-05-30T18:04:51Z", "last_pushed": "2023-05-30T09:02:46Z", "created_at": "2022-04-18T04:55:57Z", "size": 29655, "language": "TypeScript", "gitops": false, "status": "active", "license": "Apache License 2.0", "spdx_id": "Apache-2.0", "dirname": "illa"}, {"name": "changedetection.io", "description": "A self-hosted free open source website change detection, monitor and notification service.", "tags": ["monitoring"], "source": "https://github.com/dgtlmoon/changedetection.io", "website": "https://changedetection.io/", "icon": "https://changedetection.io/assets/images/favicons/apple-touch-icon.png", "screenshots": ["https://raw.githubusercontent.com/dgtlmoon/changedetection.io/master/docs/screenshot.png"], "stars": 9223, "forks": 542, "watchers": 9223, "issues": 129, "last_updated": "2023-05-30T20:10:27Z", "last_pushed": "2023-05-30T06:57:17Z", "created_at": "2021-01-27T16:03:30Z", "size": 6913, "language": "Python", "gitops": false, "status": "active", "license": "Apache License 2.0", "spdx_id": "Apache-2.0", "dirname": "changedetection"}, {"name": "Gatus", "description": "Gatus is a service that allows you to monitor the availability and latency of your services and expose this information a beautiful dashboard.", "tags": ["monitoring"], "source": "https://github.com/TwiN/gatus", "website": "https://gatus.io/", "icon": "https://raw.githubusercontent.com/TwiN/gatus/9e46e3972d382c62ebf954eb109b3c856d33bd58/web/app/public/logo-192x192.png", "screenshots": ["https://github.com/TwiN/gatus/raw/master/.github/assets/dashboard-dark.png"], "stars": 3707, "forks": 275, "watchers": 3707, "issues": 79, "last_updated": "2023-05-30T08:31:31Z", "last_pushed": "2023-05-30T06:56:02Z", "created_at": "2019-09-04T02:35:40Z", "size": 33801, "language": "Go", "gitops": false, "status": "active", "license": "Apache License 2.0", "spdx_id": "Apache-2.0", "dirname": "gatus"}, {"name": "Wiki.js", "description": "Wiki.js is a modern, lightweight and powerful wiki app built on Node.js, Git and Markdown.", "tags": ["wiki"], "source": "https://github.com/Requarks/wiki", "website": "https://js.wiki/", "icon": "https://raw.githubusercontent.com/requarks/wiki/main/client/static/favicons/android-chrome-256x256.png", "screenshots": null, "stars": 21044, "forks": 2335, "watchers": 21044, "issues": 134, "last_updated": "2023-05-30T16:16:21Z", "last_pushed": "2023-05-30T04:42:46Z", "created_at": "2016-08-16T19:35:26Z", "size": 37913, "language": "Vue", "gitops": false, "status": "active", "license": "GNU Affero General Public License v3.0", "spdx_id": "AGPL-3.0", "dirname": "wikijs"}, {"name": "umami", "description": "Umami is a simple, fast, privacy-focused alternative to Google Analytics.", "tags": ["analytics"], "source": "https://github.com/umami-software/umami", "website": "https://umami.is/", "icon": "https://avatars.githubusercontent.com/u/105618662?s=200&v=4", "screenshots": ["https://umami.is/images/languages.png"], "stars": 15921, "forks": 2733, "watchers": 15921, "issues": 108, "last_updated": "2023-05-30T18:12:16Z", "last_pushed": "2023-05-30T04:20:01Z", "created_at": "2020-07-17T07:59:00Z", "size": 8867, "language": "JavaScript", "gitops": false, "status": "active", "license": "MIT License", "spdx_id": "MIT", "dirname": "umami"}, {"name": "opengist", "description": "Self-hosted pastebin powered by Git, open-source alternative to Github Gist.", "tags": ["editor", "pastebin"], "source": "https://github.com/thomiceli/opengist", "website": "https://github.com/thomiceli/opengist", "documentation": null, "icon": "https://raw.githubusercontent.com/thomiceli/opengist/master/public/favicon.svg", "screenshots": null, "stars": 324, "forks": 18, "watchers": 324, "issues": 7, "last_updated": "2023-05-30T12:15:52Z", "last_pushed": "2023-05-29T20:39:32Z", "created_at": "2023-04-10T20:58:35Z", "size": 345, "language": "Go", "gitops": false, "status": "active", "license": "GNU Affero General Public License v3.0", "spdx_id": "AGPL-3.0", "dirname": "opengist"}, {"name": "MiroTalk P2P", "description": "WebRTC - P2P - Simple, Secure, Fast, Real-Time Video Conferences Up to 4k and 60fps, compatible with all browsers and platforms.", "tags": ["Video Conferencing"], "source": "https://github.com/miroslavpejic85/mirotalk", "website": "https://p2p.mirotalk.com", "icon": "https://www.saashub.com/images/app/service_logos/213/pgzsasbgu5fr/large.png?1653219756", "screenshots": ["https://github.com/miroslavpejic85/mirotalk/raw/master/public/images/mirotalk-header.gif"], "installationnotes": "Make sure to to change all the secrets and Passwords.", "stars": 1819, "forks": 376, "watchers": 1819, "issues": 5, "last_updated": "2023-05-29T10:12:08Z", "last_pushed": "2023-05-29T18:29:50Z", "created_at": "2021-01-01T21:31:15Z", "size": 33004, "language": "JavaScript", "gitops": false, "status": "active", "license": "GNU Affero General Public License v3.0", "spdx_id": "AGPL-3.0", "dirname": "mirotalk-p2p"}, {"name": "Unleash", "description": "Unleash is an open source feature management solution.", "tags": ["feature-toggle"], "source": "https://github.com/Unleash/unleash", "website": "https://getunleash.io/", "icon": "https://avatars.githubusercontent.com/u/23053233?s=200&v=4", "screenshots": ["https://raw.githubusercontent.com/Unleash/unleash/main/.github/github_online_demo.svg"], "stars": 7875, "forks": 512, "watchers": 7875, "issues": 53, "last_updated": "2023-05-30T18:48:27Z", "last_pushed": "2023-05-29T15:49:29Z", "created_at": "2014-09-29T12:50:46Z", "size": 130774, "language": "TypeScript", "gitops": false, "status": "active", "license": "Apache License 2.0", "spdx_id": "Apache-2.0", "dirname": "unleash"}, {"name": "Laravel", "description": "Laravel is a web application framework with expressive, elegant syntax.", "tags": ["framework", "php"], "source": "https://github.com/laravel/laravel", "website": "https://laravel.com", "icon": "https://avatars.githubusercontent.com/u/958072?s=200&v=4", "screenshots": null, "stars": 73577, "forks": 23746, "watchers": 73577, "issues": 31, "last_updated": "2023-05-30T15:00:53Z", "last_pushed": "2023-05-29T13:00:18Z", "created_at": "2011-06-08T03:06:08Z", "size": 10635, "language": "PHP", "gitops": true, "status": "active", "license": "Unknown", "spdx_id": "-", "dirname": "laravel"}, {"name": "Authorizer", "description": "Authorizer is an open-source authentication and authorization solution for your applications.", "tags": ["authentication"], "source": "https://github.com/authorizerdev/authorizer", "website": "https://authorizer.dev/", "icon": "https://authorizer.dev/images/favicon_io/android-chrome-192x192.png", "screenshots": ["https://docs.authorizer.dev/images/authorizer-arch.png"], "stars": 1036, "forks": 86, "watchers": 1036, "issues": 57, "last_updated": "2023-05-30T01:52:39Z", "last_pushed": "2023-05-29T05:03:16Z", "created_at": "2021-06-02T12:42:07Z", "size": 10882, "language": "Go", "gitops": false, "status": "active", "license": "MIT License", "spdx_id": "MIT", "dirname": "authorizer"}, {"name": "Gotify", "description": "Gotify is a simple server for sending and receiving messages (in real time per WebSocket)", "tags": ["monitoring"], "source": "https://github.com/gotify/server", "website": "https://gotify-net", "icon": "https://raw.githubusercontent.com/gotify/logo/master/gotify-logo.png", "screenshots": ["https://github.com/gotify/server/raw/master/ui.png"], "stars": 8775, "forks": 502, "watchers": 8775, "issues": 43, "last_updated": "2023-05-30T08:48:00Z", "last_pushed": "2023-05-28T13:59:50Z", "created_at": "2018-01-15T20:25:27Z", "size": 3743, "language": "Go", "gitops": false, "status": "active", "license": "Other", "spdx_id": "NOASSERTION", "dirname": "gotify"}, {"name": "CyberChef", "description": "CyberChef is a simple, intuitive web app for carrying out all manner of \"cyber\" operations within a web browser.", "tags": ["helper tools"], "source": "https://github.com/gchq/CyberChef", "website": "https://github.com/gchq/CyberChef", "icon": "https://www.freepnglogos.com/uploads/chef-png/chef-icon-33.png", "screenshots": null, "stars": 21305, "forks": 2505, "watchers": 21305, "issues": 376, "last_updated": "2023-05-30T19:28:18Z", "last_pushed": "2023-05-28T01:39:39Z", "created_at": "2016-11-28T10:34:07Z", "size": 88589, "language": "JavaScript", "gitops": false, "status": "active", "license": "Apache License 2.0", "spdx_id": "Apache-2.0", "dirname": "cyberchef"}, {"name": "Dashy", "description": "Dashy helps you organize your self-hosted services by making them accessible from a single place.", "tags": ["dashboard"], "source": "https://github.com/Lissy93/dashy", "website": "https://dashy.to/", "icon": "https://i.ibb.co/yhbt6CY/dashy.png", "screenshots": ["https://i.ibb.co/L8YbNNc/dashy-demo2.gif"], "stars": 11695, "forks": 873, "watchers": 11695, "issues": 71, "last_updated": "2023-05-30T17:26:26Z", "last_pushed": "2023-05-28T01:30:26Z", "created_at": "2021-02-28T10:35:44Z", "size": 346363, "language": "Vue", "gitops": false, "status": "active", "license": "MIT License", "spdx_id": "MIT", "dirname": "dashy"}, {"name": "Vaultwarden", "description": "A Bitwarden compatible paswordsafe server written in Rust. ", "tags": ["password manager", "password storage"], "source": "https://github.com/dani-garcia/vaultwarden", "website": "https://github.com/dani-garcia/vaultwarden", "icon": "https://raw.githubusercontent.com/dani-garcia/vaultwarden/main/resources/vaultwarden-icon.svg", "screenshots": null, "stars": 25321, "forks": 1276, "watchers": 25321, "issues": 13, "last_updated": "2023-05-30T17:34:40Z", "last_pushed": "2023-05-26T16:03:45Z", "created_at": "2018-02-17T22:40:20Z", "size": 8259, "language": "Rust", "gitops": false, "status": "active", "license": "GNU Affero General Public License v3.0", "spdx_id": "AGPL-3.0", "dirname": "vaultwarden"}, {"name": "Rallly", "description": "Rallly is an open-source scheduling and collaboration tool designed to make organizing events and meetings easier.", "tags": ["collaboration", "scheduling"], "source": "https://github.com/lukevella/rallly", "website": "https://rallly.co", "documentation": ["https://github.com/lukevella/rallly-selfhosted"], "icon": "https://rallly.co/favicon-196x196.png", "screenshots": ["https://raw.githubusercontent.com/lukevella/rallly/main/docs/images/poll-image.png"], "stars": 2066, "forks": 194, "watchers": 2066, "issues": 13, "last_updated": "2023-05-30T07:44:43Z", "last_pushed": "2023-05-26T11:26:02Z", "created_at": "2015-01-27T17:01:38Z", "size": 11593, "language": "TypeScript", "gitops": false, "status": "active", "license": "GNU Affero General Public License v3.0", "spdx_id": "AGPL-3.0", "dirname": "rallly"}, {"name": "Whoogle", "description": "Whoogle is a self-hosted, ad-free, privacy-respecting metasearch engine.", "tags": ["Search"], "source": "https://github.com/benbusby/whoogle-search", "website": "https://github.com/benbusby/whoogle-search", "icon": "https://preview.redd.it/4alqumb2xqi81.png?width=192&format=png&auto=webp&s=05f078627d3b9d7f1f82e002d5388efc6ee3c63a", "screenshots": ["https://raw.githubusercontent.com/benbusby/whoogle-search/main/docs/screenshot_desktop.png", "https://raw.githubusercontent.com/benbusby/whoogle-search/main/docs/screenshot_mobile.png"], "stars": 7436, "forks": 798, "watchers": 7436, "issues": 49, "last_updated": "2023-05-30T19:14:09Z", "last_pushed": "2023-05-25T21:51:55Z", "created_at": "2020-01-21T20:22:33Z", "size": 2548, "language": "Python", "gitops": false, "status": "active", "license": "MIT License", "spdx_id": "MIT", "dirname": "whoogle"}, {"name": "Homer", "description": "A dead simple static HOMepage for your servER to keep your services on hand, from a simple yaml configuration file.", "tags": ["homepage", "dashboard"], "source": "https://github.com/bastienwirtz/homer", "website": "https://github.com/bastienwirtz/homer", "icon": "https://raw.githubusercontent.com/bastienwirtz/homer/main/public/logo.png", "screenshots": ["https://camo.githubusercontent.com/22f0b90b2c9ec4f1c9ec9ed920bb7b794bc1f1ac93bf61099ef298369b8850e5/68747470733a2f2f7261772e6769746875622e636f6d2f6261737469656e776972747a2f686f6d65722f6d61696e2f646f63732f73637265656e73686f742e706e67"], "stars": 7109, "forks": 673, "watchers": 7109, "issues": 136, "last_updated": "2023-05-30T09:33:00Z", "last_pushed": "2023-05-22T05:13:16Z", "created_at": "2018-06-14T04:57:54Z", "size": 4476, "language": "Vue", "gitops": false, "status": "active", "license": "Apache License 2.0", "spdx_id": "Apache-2.0", "dirname": "homer"}, {"name": "Etherpad", "description": "Etherpad is a real-time collaborative editor scalable to thousands of simultaneous real time users.", "tags": ["collaboration", "documents", "editor", "writing"], "source": "https://github.com/ether/etherpad-lite", "website": "https://etherpad.org/", "documentation": ["https://github.com/ether/etherpad-lite/blob/develop/doc/docker.md"], "icon": "https://avatars.githubusercontent.com/u/181731?s=200&v=4", "screenshots": ["https://raw.githubusercontent.com/ether/etherpad-lite/develop/doc/images/etherpad_demo.gif"], "stars": 14321, "forks": 2540, "watchers": 14321, "issues": 177, "last_updated": "2023-05-30T18:46:43Z", "last_pushed": "2023-05-18T11:03:57Z", "created_at": "2011-03-26T13:09:02Z", "size": 34501, "language": "JavaScript", "gitops": false, "status": "active", "license": "Apache License 2.0", "spdx_id": "Apache-2.0", "dirname": "etherpad"}, {"name": "Passbolt", "description": "The open source password manager for teams", "tags": ["password", "security"], "source": "https://github.com/passbolt/passbolt_api", "website": "https://www.passbolt.com", "icon": "https://avatars.githubusercontent.com/u/4386228?s=200&v=4", "screenshots": ["https://raw.githubusercontent.com/passbolt/passbolt_styleguide/master/src/img/screenshots/teaser-screenshot-login.png", "https://raw.githubusercontent.com/passbolt/passbolt_styleguide/master/src/img/screenshots/teaser-screenshot-share.png", "https://raw.githubusercontent.com/passbolt/passbolt_styleguide/master/src/img/screenshots/teaser-screenshot4.png"], "stars": 3792, "forks": 277, "watchers": 3792, "issues": 27, "last_updated": "2023-05-30T18:03:07Z", "last_pushed": "2023-05-18T07:16:31Z", "created_at": "2016-02-23T01:14:59Z", "size": 131944, "language": "PHP", "gitops": false, "status": "active", "license": "GNU Affero General Public License v3.0", "spdx_id": "AGPL-3.0", "dirname": "passbolt"}, {"name": "Tasks.md", "description": "A self-hosted, file based task management board that supports Markdown syntax.", "tags": ["scrumboard", "kanban", "task", "todo", "list", "markdown", "markdown-editor"], "source": "https://github.com/BaldissaraMatheus/Tasks.md", "website": "https://hub.docker.com/r/baldissaramatheus/tasks.md", "icon": "https://raw.githubusercontent.com/BaldissaraMatheus/Tasks.md/main/frontend/public/favicon/android-chrome-192x192.png", "screenshots": ["https://raw.githubusercontent.com/BaldissaraMatheus/Tasks.md/main/public/demonstration.gif"], "stars": 134, "forks": 6, "watchers": 134, "issues": 6, "last_updated": "2023-05-27T17:21:24Z", "last_pushed": "2023-05-11T19:55:34Z", "created_at": "2023-02-26T21:19:33Z", "size": 748, "language": "JavaScript", "gitops": false, "status": "active", "license": "MIT License", "spdx_id": "MIT", "dirname": "tasksmd"}, {"name": "TimeTagger", "description": "TimeTagger is a simple time tracking tool for your terminal.", "tags": ["Time tracking"], "source": "https://github.com/almarklein/timetagger", "website": "https://timetagger.app/", "icon": "https://timetagger.app/timetagger_sl.svg", "screenshots": ["https://timetagger.app/screenshot1.png", "https://timetagger.app/screenshot2.png", "https://timetagger.app/screenshot3.png"], "stars": 718, "forks": 66, "watchers": 718, "issues": 42, "last_updated": "2023-05-29T07:04:07Z", "last_pushed": "2023-05-07T15:53:17Z", "created_at": "2020-12-30T11:29:32Z", "size": 3623, "language": "Python", "gitops": false, "status": "active", "license": "GNU General Public License v3.0", "spdx_id": "GPL-3.0", "dirname": "timetagger"}, {"name": "Shiori", "description": "Shiori is a simple bookmark manager. ", "tags": ["bookmark manager"], "source": "https://github.com/go-shiori/shiori", "website": "https://github.com/go-shiori/shiori", "icon": "https://raw.githubusercontent.com/go-shiori/shiori/master/internal/view/res/apple-touch-icon-152x152.png", "screenshots": ["https://raw.githubusercontent.com/go-shiori/shiori/master/docs/readme/cover.png", "https://raw.githubusercontent.com/go-shiori/shiori/master/docs/screenshots/02-home.png", "https://raw.githubusercontent.com/go-shiori/shiori/master/docs/screenshots/04-options.png"], "stars": 7346, "forks": 489, "watchers": 7346, "issues": 56, "last_updated": "2023-05-30T08:51:09Z", "last_pushed": "2023-05-04T06:14:58Z", "created_at": "2018-01-23T13:57:11Z", "size": 44794, "language": "JavaScript", "gitops": false, "status": "active", "license": "MIT License", "spdx_id": "MIT", "dirname": "shiori"}, {"name": "Maputnik", "description": "A free and open visual editor for the Mapbox GL styles targeted at developers and map designers.", "tags": ["mapping", "maps", "cartography"], "source": "https://github.com/maputnik/editor", "website": "https://maputnik.github.io/editor/", "icon": "https://avatars.githubusercontent.com/u/22297422?s=200&v=4", "screenshots": ["https://camo.githubusercontent.com/e417a4c766f2f3245803f93ed2bdad17d13f20d114330e2436f91ecfadd1e7bf/68747470733a2f2f6a2e676966732e636f6d2f6b3567384f4a2e676966"], "stars": 1743, "forks": 336, "watchers": 1743, "issues": 96, "last_updated": "2023-05-30T12:16:54Z", "last_pushed": "2023-04-21T20:16:18Z", "created_at": "2016-09-08T17:52:22Z", "size": 14212, "language": "JavaScript", "gitops": false, "status": "active", "license": "MIT License", "spdx_id": "MIT", "dirname": "maputnik"}, {"name": "Traggo", "description": "Traggo is a self-hosted time tracking tool. It is designed to be easy to use and to be self-hosted. It is written in Go and uses Vue.js for the frontend. ", "tags": ["time tracking", "time management"], "source": "https://github.com/traggo/server", "website": "https://traggo.org", "icon": "https://raw.githubusercontent.com/traggo/logo/master/logo.png", "screenshots": ["https://github.com/traggo/server/raw/master/.github/traggo_list.png", "https://github.com/traggo/server/raw/master/.github/traggo_calendar.png", "https://github.com/traggo/server/raw/master/.github/traggo_dashboard.png"], "stars": 758, "forks": 42, "watchers": 758, "issues": 41, "last_updated": "2023-05-27T19:42:04Z", "last_pushed": "2023-02-14T08:19:35Z", "created_at": "2018-12-08T17:58:45Z", "size": 1409, "language": "Go", "gitops": false, "status": "active", "license": "GNU General Public License v3.0", "spdx_id": "GPL-3.0", "dirname": "traggo"}]}